{
    "forecast_data": {
        "location": {
            "name": "Boston",
            "state": "MA",
            "latitude": 42.287,
            "longitude": -71.133
        },
        "current_conditions": {
            "timestamp": "2026-07-21T17:05:00+00:00",
            "temperature_f": 77.0,
            "temperature_c": 25,
            "humidity": 57.393288213137,
            "wind_speed_mph": 28.991520000000005,
            "wind_direction": 170,
            "description": "Partly Cloudy"
        },
        "forecast": [
            {
                "number": 1,
                "name": "This Afternoon",
                "startTime": "2026-07-21T13:00:00-04:00",
                "endTime": "2026-07-21T18:00:00-04:00",
                "isDaytime": true,
                "temperature": 83,
                "temperatureUnit": "F",
                "temperatureTrend": null,
                "probabilityOfPrecipitation": {
                    "unitCode": "wmoUnit:percent",
                    "value": 32
                },
                "windSpeed": "13 mph",
                "windDirection": "S",
                "icon": "https://api.weather.gov/icons/land/day/tsra,30?size=medium",
                "shortForecast": "Chance Showers And Thunderstorms",
                "detailedForecast": "A slight chance of rain showers between 3pm and 5pm, then a chance of showers and thunderstorms. Mostly cloudy, with a high near 83. South wind around 13 mph, with gusts as high as 24 mph. Chance of precipitation is 30%. New rainfall amounts less than a tenth of an inch possible."
            },
            {
                "number": 2,
                "name": "Tonight",
                "startTime": "2026-07-21T18:00:00-04:00",
                "endTime": "2026-07-22T06:00:00-04:00",
                "isDaytime": false,
                "temperature": 68,
                "temperatureUnit": "F",
                "temperatureTrend": null,
                "probabilityOfPrecipitation": {
                    "unitCode": "wmoUnit:percent",
                    "value": 89
                },
                "windSpeed": "13 mph",
                "windDirection": "S",
                "icon": "https://api.weather.gov/icons/land/night/tsra,90/tsra,70?size=medium",
                "shortForecast": "Showers And Thunderstorms",
                "detailedForecast": "Showers and thunderstorms. Cloudy, with a low around 68. South wind around 13 mph, with gusts as high as 25 mph. Chance of precipitation is 90%. New rainfall amounts between a half and three quarters of an inch possible."
            }
        ]
    },
    "weather_report": "As the afternoon unfolds in Boston, a thick layer of clouds blankets the sky, hinting at the possibility of light rain showers intermingled with the heat of the day. Despite the warmth that lingers, with temperatures flirting with the low 80s, the outlook is preoccupied with the dark promises of thunderstorms looming on the horizon. The air carries a softness, tentatively stirred by a gentle south wind, yet the anticipation of rain transforms the afternoon into a mosaic of uncertainty. \n\nAs evening descends, expect a deeper embrace of clouds and an increase in rainfall, with thunderstorms ready to fill the air with their electric music. The temperature will wane, offering a more humid night, where the remnants of warmth mingle with the cooling embrace of rain. One might consider attire that accommodates these shifting moods\u2014lighter layers that can easily adapt and a water-resistant jacket to stave off the impending showers. For those seeking to linger outside, a stroll under the muted sky might beckon, perhaps with a caf\u00e9 stop to shelter from the rain while contemplating the theater of the elements. While the day\u2019s charm may seem overshadowed by the gloom, there\u2019s always a beauty in nature's tempestuous dance.",
    "color_code": "#A0A0A0",
    "timestamp": "2026-07-21 13:26:31"
}