{
    "forecast_data": {
        "location": {
            "name": "Brookline",
            "state": "MA",
            "latitude": 42.287,
            "longitude": -71.133
        },
        "current_conditions": {
            "timestamp": "2026-06-06T16:20:00+00:00",
            "temperature_f": 82.4,
            "temperature_c": 28,
            "humidity": 51.245730319259,
            "wind_speed_mph": 33.17918400000001,
            "wind_direction": 200,
            "description": "Clear"
        },
        "forecast": [
            {
                "number": 1,
                "name": "This Afternoon",
                "startTime": "2026-06-06T12:00:00-04:00",
                "endTime": "2026-06-06T18:00:00-04:00",
                "isDaytime": true,
                "temperature": 87,
                "temperatureUnit": "F",
                "temperatureTrend": null,
                "probabilityOfPrecipitation": {
                    "unitCode": "wmoUnit:percent",
                    "value": 8
                },
                "windSpeed": "10 to 14 mph",
                "windDirection": "SW",
                "icon": "https://api.weather.gov/icons/land/day/bkn?size=medium",
                "shortForecast": "Mostly Cloudy",
                "detailedForecast": "Mostly cloudy, with a high near 87. Southwest wind 10 to 14 mph, with gusts as high as 25 mph."
            },
            {
                "number": 2,
                "name": "Tonight",
                "startTime": "2026-06-06T18:00:00-04:00",
                "endTime": "2026-06-07T06:00:00-04:00",
                "isDaytime": false,
                "temperature": 66,
                "temperatureUnit": "F",
                "temperatureTrend": null,
                "probabilityOfPrecipitation": {
                    "unitCode": "wmoUnit:percent",
                    "value": 60
                },
                "windSpeed": "9 to 13 mph",
                "windDirection": "SW",
                "icon": "https://api.weather.gov/icons/land/night/tsra_hi,60/tsra_hi,30?size=medium",
                "shortForecast": "Showers And Thunderstorms Likely",
                "detailedForecast": "Showers and thunderstorms likely between 8pm and 2am. Partly cloudy, with a low around 66. Southwest wind 9 to 13 mph, with gusts as high as 23 mph. Chance of precipitation is 60%. New rainfall amounts less than a tenth of an inch possible."
            }
        ]
    },
    "weather_report": "In Boston this afternoon, a shroud of clouds blankets the sky, casting a muted light over the city and its surroundings. Those who venture outside might feel the warm embrace of summer, with temperatures hovering near the upper 80s. However, the southwest winds, playful as they are, bring with them the promise of gusty moments, stirring the leaves in a gentle dance. The air carries a palpable tension; a hint of moisture foretells the likelihood of showers and thunderstorms later in the evening, as nature readies for a dramatic turn.\n\nAs twilight approaches, the heavens are poised to release their burden, ushering in a cooling spell that will bring temperatures down to the mid-60s. While the weather invites one to enjoy the day outdoors, it\u2019s prudent to have a light jacket or a trusty umbrella at hand for the evening drizzle. Today isn\u2019t meant for grand gestures but for quiet pleasures\u2014perhaps a stroll through the park, a visit to a cozy caf\u00e9, or a moment spent pondering along the waterfront, absorbing the beauty of a day in flux, before the night weeps its gentle rain. Prepare for the unexpected, for this afternoon carries the weight of both warmth and a refreshing promise of relief in the hours ahead.",
    "color_code": "#B0C4D6",
    "timestamp": "2026-06-06 12:31:23"
}