{
    "forecast_data": {
        "location": {
            "name": "Brookline",
            "state": "MA",
            "latitude": 42.287,
            "longitude": -71.133
        },
        "current_conditions": {
            "timestamp": "2025-05-01T02:53:00+00:00",
            "temperature_f": 55.94,
            "temperature_c": 13.3,
            "humidity": 27.674183782626,
            "wind_speed_mph": 12.0798,
            "wind_direction": 340,
            "description": "Clear"
        },
        "forecast": [
            {
                "number": 1,
                "name": "Overnight",
                "startTime": "2025-05-01T00:00:00-04:00",
                "endTime": "2025-05-01T06:00:00-04:00",
                "isDaytime": false,
                "temperature": 41,
                "temperatureUnit": "F",
                "temperatureTrend": "",
                "probabilityOfPrecipitation": {
                    "unitCode": "wmoUnit:percent",
                    "value": null
                },
                "windSpeed": "2 to 7 mph",
                "windDirection": "NW",
                "icon": "https://api.weather.gov/icons/land/night/few?size=medium",
                "shortForecast": "Mostly Clear",
                "detailedForecast": "Mostly clear, with a low around 41. Northwest wind 2 to 7 mph."
            },
            {
                "number": 2,
                "name": "Thursday",
                "startTime": "2025-05-01T06:00:00-04:00",
                "endTime": "2025-05-01T18:00:00-04:00",
                "isDaytime": true,
                "temperature": 70,
                "temperatureUnit": "F",
                "temperatureTrend": "",
                "probabilityOfPrecipitation": {
                    "unitCode": "wmoUnit:percent",
                    "value": null
                },
                "windSpeed": "2 to 7 mph",
                "windDirection": "E",
                "icon": "https://api.weather.gov/icons/land/day/few?size=medium",
                "shortForecast": "Sunny",
                "detailedForecast": "Sunny, with a high near 70. East wind 2 to 7 mph."
            }
        ]
    },
    "weather_report": "As the night deepens, Boston settles into a quiet serenity, blanketed by a mostly clear sky that hints at the promise of a beautiful day ahead. With temperatures dipping to a cool 41 degrees, you may want to wrap yourself in a light jacket or cozy sweater if you're stepping outside in these early hours. A gentle northwest wind whispers softly, dancing through the stillness, while the twinkling city lights create a tapestry of warmth against the black canvas of the night.\n\nUpon the dawn, a splendid transformation awaits. Thursday will unveil itself with a brilliant sun; a welcoming embrace of warmth is expected to rise near 70 degrees, inviting all to bask in its glow. The air will shift slightly as an easterly breeze stirs, perfect for leisurely strolls down the Charles River or perhaps indulging in a quaint caf\u00e9's offerings while enjoying the morning light. A day like this beckons exploration\u2014be it meandering through the Boston Commons or visiting the local markets, where the vibrant colors of spring\u2019s produce stand in stark contrast to winter\u2019s remnants. Don yourself in comfortable layers; a light shirt might suffice later, but keep that jacket close for the early morning's gentle chill. Today, the city calls for gentle beginnings before cascading into joyful pursuits under the sun's warm gaze\u2014each moment a reminder of the beauty found in a serene spring day.",
    "color_code": "#76B5D8",
    "timestamp": "2025-05-01 00:11:22"
}