{
    "forecast_data": {
        "location": {
            "name": "Brookline",
            "state": "MA",
            "latitude": 42.287,
            "longitude": -71.133
        },
        "current_conditions": {
            "timestamp": "2025-11-16T19:50:00+00:00",
            "temperature_f": 48.2,
            "temperature_c": 9,
            "humidity": null,
            "wind_speed_mph": null,
            "wind_direction": null,
            "description": "Mostly Clear"
        },
        "forecast": [
            {
                "number": 1,
                "name": "This Afternoon",
                "startTime": "2025-11-16T15:00:00-05:00",
                "endTime": "2025-11-16T18:00:00-05:00",
                "isDaytime": true,
                "temperature": 52,
                "temperatureUnit": "F",
                "temperatureTrend": "",
                "probabilityOfPrecipitation": {
                    "unitCode": "wmoUnit:percent",
                    "value": 5
                },
                "windSpeed": "16 mph",
                "windDirection": "W",
                "icon": "https://api.weather.gov/icons/land/day/bkn?size=medium",
                "shortForecast": "Partly Sunny",
                "detailedForecast": "Partly sunny. High near 52, with temperatures falling to around 42 in the afternoon. West wind around 16 mph, with gusts as high as 30 mph."
            },
            {
                "number": 2,
                "name": "Tonight",
                "startTime": "2025-11-16T18:00:00-05:00",
                "endTime": "2025-11-17T06:00:00-05:00",
                "isDaytime": false,
                "temperature": 31,
                "temperatureUnit": "F",
                "temperatureTrend": "",
                "probabilityOfPrecipitation": {
                    "unitCode": "wmoUnit:percent",
                    "value": 6
                },
                "windSpeed": "15 mph",
                "windDirection": "W",
                "icon": "https://api.weather.gov/icons/land/night/sct?size=medium",
                "shortForecast": "Partly Cloudy",
                "detailedForecast": "Partly cloudy, with a low around 31. West wind around 15 mph, with gusts as high as 30 mph."
            }
        ]
    },
    "weather_report": "In Boston this afternoon, the sky dons a quilt of clouds, one that allows glimmers of sunlight to play upon the earth, though the warmth is fleeting. The brisk west wind, whispering through the streets, brings a chill that reminds you winter is approaching. From the heights of the Blue Hill Observatory, the view stretches clear and unmarred, offering a gentle reminder of the stunning interplay between light and shadow that this season bestows upon the landscape. The temperature dips into the lower 40s, inviting a thoughtful selection of attire\u2014a snug sweater layered under a jacket should suffice, accompanied by a sturdy scarf to guard against the crisp breezes.\n\nAs dusk approaches, the weather shifts to a more subdued palette, where the evening promises to wrap the city in a cooler embrace, depths falling to about 31 degrees. The clouds shift to a softer gray, yet remain high enough to encourage those reluctant to retreat indoors. A walk through the quieter neighborhoods might yield serene moments, perhaps wandering along the Charles River, where the sight of fading light glistening off the water offers a tranquil end to the day. Alternatively, this brisk afternoon and evening is prime for gathering around a cozy caf\u00e9, savoring a warm drink while the world outside embraces the chill with a muted grace.",
    "color_code": "#A4C8E1",
    "timestamp": "2025-11-16 15:07:49"
}