{
    "forecast_data": {
        "location": {
            "name": "Brookline",
            "state": "MA",
            "latitude": 42.287,
            "longitude": -71.133
        },
        "current_conditions": {
            "timestamp": "2026-01-17T15:50:00+00:00",
            "temperature_f": 35.6,
            "temperature_c": 2,
            "humidity": 64.482018531034,
            "wind_speed_mph": 12.401928,
            "wind_direction": 230,
            "description": "Cloudy"
        },
        "forecast": [
            {
                "number": 1,
                "name": "Today",
                "startTime": "2026-01-17T11:00:00-05:00",
                "endTime": "2026-01-17T18:00:00-05:00",
                "isDaytime": true,
                "temperature": 44,
                "temperatureUnit": "F",
                "temperatureTrend": null,
                "probabilityOfPrecipitation": {
                    "unitCode": "wmoUnit:percent",
                    "value": 62
                },
                "windSpeed": "9 mph",
                "windDirection": "SW",
                "icon": "https://api.weather.gov/icons/land/day/rain,40/rain,60?size=medium",
                "shortForecast": "Light Rain Likely",
                "detailedForecast": "Rain likely. Mostly cloudy, with a high near 44. Southwest wind around 9 mph. Chance of precipitation is 60%. New rainfall amounts less than a tenth of an inch possible."
            },
            {
                "number": 2,
                "name": "Tonight",
                "startTime": "2026-01-17T18:00:00-05:00",
                "endTime": "2026-01-18T06:00:00-05:00",
                "isDaytime": false,
                "temperature": 30,
                "temperatureUnit": "F",
                "temperatureTrend": null,
                "probabilityOfPrecipitation": {
                    "unitCode": "wmoUnit:percent",
                    "value": 23
                },
                "windSpeed": "6 mph",
                "windDirection": "SW",
                "icon": "https://api.weather.gov/icons/land/night/rain,20/bkn?size=medium",
                "shortForecast": "Slight Chance Light Rain then Mostly Cloudy",
                "detailedForecast": "A slight chance of rain before 7pm, then patchy fog between 7pm and 9pm. Mostly cloudy, with a low around 30. Southwest wind around 6 mph. Chance of precipitation is 20%."
            }
        ]
    },
    "weather_report": "In Boston, a muted gray canopy hangs overhead, casting a quiet gloom over the city as the day unfolds. Rain is poised to grace the landscape, with a promise of moisture that will likely drench the cobblestones and sidewalks. The air is filled with a gentle chill that suggests the presence of dampness in every breath. With the temperatures hovering around the mid-forties, the scene feels a touch bleak, but there\u2019s a sense of calm that accompanies the overcast skies. For those venturing outdoors, layering is advisable\u2014think a warm sweater beneath a reliable raincoat, perhaps favoring practicality over fashion as the brisk southwest wind whispers through the trees.\n\nAs twilight nears and the evening beckons, only a hint of rain remains, giving way to an atmospheric dance with patchy fog. This fog, while perhaps lending an ethereal quality to the landscape, also invites a slower pace\u2014a perfect backdrop for quiet reflection or an unhurried stroll along the riverbanks. Nature may draw you outside, but today also tilts toward the delights of indoor comforts. Picture yourself enveloped in the warmth of a favorite caf\u00e9, sipping on a hot brew and watching the world fade quietly into dusk. There\u2019s beauty in this drabness; embrace it with a deep breath and a gentle heart.",
    "color_code": "#B0B0B0",
    "timestamp": "2026-01-17 11:08:08"
}