{
    "forecast_data": {
        "location": {
            "name": "Brookline",
            "state": "MA",
            "latitude": 42.287,
            "longitude": -71.133
        },
        "current_conditions": {
            "timestamp": "2024-12-17T18:53:00+00:00",
            "temperature_f": 62.059999999999995,
            "temperature_c": 16.7,
            "humidity": 47.891073844362,
            "wind_speed_mph": 53.95644000000001,
            "wind_direction": 260,
            "description": "Clear"
        },
        "forecast": [
            {
                "number": 1,
                "name": "This Afternoon",
                "startTime": "2024-12-17T15:00:00-05:00",
                "endTime": "2024-12-17T18:00:00-05:00",
                "isDaytime": true,
                "temperature": 56,
                "temperatureUnit": "F",
                "temperatureTrend": "",
                "probabilityOfPrecipitation": {
                    "unitCode": "wmoUnit:percent",
                    "value": null
                },
                "windSpeed": "8 mph",
                "windDirection": "W",
                "icon": "https://api.weather.gov/icons/land/day/sct?size=medium",
                "shortForecast": "Mostly Sunny",
                "detailedForecast": "Mostly sunny, with a high near 56. West wind around 8 mph."
            },
            {
                "number": 2,
                "name": "Tonight",
                "startTime": "2024-12-17T18:00:00-05:00",
                "endTime": "2024-12-18T06:00:00-05:00",
                "isDaytime": false,
                "temperature": 33,
                "temperatureUnit": "F",
                "temperatureTrend": "",
                "probabilityOfPrecipitation": {
                    "unitCode": "wmoUnit:percent",
                    "value": null
                },
                "windSpeed": "9 mph",
                "windDirection": "W",
                "icon": "https://api.weather.gov/icons/land/night/sct?size=medium",
                "shortForecast": "Partly Cloudy",
                "detailedForecast": "Partly cloudy, with a low around 33. West wind around 9 mph."
            }
        ]
    },
    "weather_report": "As the sun casts a gentle light over Boston this afternoon, the weather manifests a dance of warmth and coolness, a reminder of the seasonal transition. With a high nearing 56 degrees, the sky is mostly sunny and adorned with playful clouds that drift lazily, while a mild west wind carries a crispness in its embrace. The city, under this bright canopy, feels invigorated, urging its inhabitants to step outside and relish the fleeting clarity of the day. As evening approaches, the temperature will gracefully descend to around 33 degrees, leading into a partly cloudy night that invites layers and warmth.\n\nFor those heading out, a light jacket or sweater will offer comfort against the coolness of the evening air. Perhaps a leisurely stroll along the Charles River could provide a moment of serenity, where reflections shimmer on the water's surface, enhancing the tranquil spirit of the day. If one leans towards a touch of creativity, a warm caf\u00e9 beckons, where the aroma of fresh coffee and freshly baked pastries creates a cozy retreat. There\u2019s a promise in the air today, a gentle push towards enjoying the little moments that make this winter day in Boston not just bearable but quite delightful.",
    "color_code": "#A3C2D4",
    "timestamp": "2024-12-17 15:07:25"
}