{
    "forecast_data": {
        "location": {
            "name": "Brookline",
            "state": "MA",
            "latitude": 42.287,
            "longitude": -71.133
        },
        "current_conditions": {
            "timestamp": "2025-07-27T01:53:00+00:00",
            "temperature_f": 66.02,
            "temperature_c": 18.9,
            "humidity": 69.959500486126,
            "wind_speed_mph": 12.0798,
            "wind_direction": 170,
            "description": "Clear"
        },
        "forecast": [
            {
                "number": 1,
                "name": "Overnight",
                "startTime": "2025-07-27T00:00:00-04:00",
                "endTime": "2025-07-27T06:00:00-04:00",
                "isDaytime": false,
                "temperature": 61,
                "temperatureUnit": "F",
                "temperatureTrend": "",
                "probabilityOfPrecipitation": {
                    "unitCode": "wmoUnit:percent",
                    "value": 1
                },
                "windSpeed": "7 mph",
                "windDirection": "SW",
                "icon": "https://api.weather.gov/icons/land/night/bkn?size=medium",
                "shortForecast": "Mostly Cloudy",
                "detailedForecast": "Mostly cloudy, with a low around 61. Southwest wind around 7 mph."
            },
            {
                "number": 2,
                "name": "Sunday",
                "startTime": "2025-07-27T06:00:00-04:00",
                "endTime": "2025-07-27T18:00:00-04:00",
                "isDaytime": true,
                "temperature": 76,
                "temperatureUnit": "F",
                "temperatureTrend": "",
                "probabilityOfPrecipitation": {
                    "unitCode": "wmoUnit:percent",
                    "value": 71
                },
                "windSpeed": "7 to 10 mph",
                "windDirection": "S",
                "icon": "https://api.weather.gov/icons/land/day/rain_showers,50/rain_showers,70?size=medium",
                "shortForecast": "Rain Showers Likely",
                "detailedForecast": "Rain showers likely after 9am. Mostly cloudy, with a high near 76. South wind 7 to 10 mph. Chance of precipitation is 70%. New rainfall amounts less than a tenth of an inch possible."
            }
        ]
    },
    "weather_report": "As the clock reaches the quiet hours of early morning, the skies over Boston hold a soft veil of clouds, ushering in a gentle night. With temperatures settling into the low sixties, a mild southwest breeze carries the aromas of summer, hinting at the promise of warmth under the day's anticipated veil of gray. As dawn breaks, the air will awaken with the likelihood of rain showers\u2014familiar to Bostonians\u2014arriving gently after nine o'clock. The day promises a high around seventy-six, cloaked in the embrace of a south wind.\n\nGiven these conditions, one might find the day to be a mixed blessing. While the clouds and potential showers may deter outdoor activities, they create an enchanting atmosphere perfect for savoring a quiet morning coffee by the window, or perhaps diving into a good book. Layering is advisable; a light jacket or umbrella may be prudent as the skies occasionally weep. For those who prefer to embrace the day, a leisurely stroll through a nearby park could reveal hidden beauties in the muted light, while the ambiance of rain might lend itself beautifully to the warmth of a cozy caf\u00e9. As the rain gently patters on the pavement, the city will breathe with life, inviting a slower pace amidst the rhythm of the season.",
    "color_code": "#B0C4D1",
    "timestamp": "2025-07-27 00:23:38"
}