{
    "forecast_data": {
        "location": {
            "name": "Brookline",
            "state": "MA",
            "latitude": 42.287,
            "longitude": -71.133
        },
        "current_conditions": {
            "timestamp": "2026-01-02T19:50:00+00:00",
            "temperature_f": 26.6,
            "temperature_c": -3,
            "humidity": null,
            "wind_speed_mph": 41.39344800000001,
            "wind_direction": 270,
            "description": "Clear"
        },
        "forecast": [
            {
                "number": 1,
                "name": "This Afternoon",
                "startTime": "2026-01-02T15:00:00-05:00",
                "endTime": "2026-01-02T18:00:00-05:00",
                "isDaytime": true,
                "temperature": 27,
                "temperatureUnit": "F",
                "temperatureTrend": null,
                "probabilityOfPrecipitation": {
                    "unitCode": "wmoUnit:percent",
                    "value": 0
                },
                "windSpeed": "9 mph",
                "windDirection": "W",
                "icon": "https://api.weather.gov/icons/land/day/sct?size=medium",
                "shortForecast": "Mostly Sunny",
                "detailedForecast": "Mostly sunny, with a high near 27. West wind around 9 mph."
            },
            {
                "number": 2,
                "name": "Tonight",
                "startTime": "2026-01-02T18:00:00-05:00",
                "endTime": "2026-01-03T06:00:00-05:00",
                "isDaytime": false,
                "temperature": 17,
                "temperatureUnit": "F",
                "temperatureTrend": null,
                "probabilityOfPrecipitation": {
                    "unitCode": "wmoUnit:percent",
                    "value": 1
                },
                "windSpeed": "7 mph",
                "windDirection": "W",
                "icon": "https://api.weather.gov/icons/land/night/few?size=medium",
                "shortForecast": "Mostly Clear",
                "detailedForecast": "Mostly clear, with a low around 17. West wind around 7 mph."
            }
        ]
    },
    "weather_report": "In Boston this afternoon, the air is crisp and inviting, with a mostly sunny sky casting a warm glow over the city. The temperature nudges towards a pleasant warmth, just touching the high mark of mid-summer-like warmth, accompanied by a gentle westerly breeze that whispers through the streets. As the daylight wanes into evening, a clear sky promises to cradle the city in tranquility, wrapping it in cooler but still bearable temperatures. The evening's chill will settle around the low of 17 degrees, a reminder of winter's presence, but the westerly winds remain light, allowing for a stroll without too much discomfort.\n\nIn such splendid conditions, one might consider wearing layered clothing\u2014perhaps a comfortable sweater under a tailored coat, along with warm yet stylish boots to navigate the evening's chill. With the sun\u2019s light fading, this is an ideal moment to wander through the winding streets of the city or perhaps grab a warm drink at a local caf\u00e9. For those who seek a bit more adventure, a leisurely walk along the Charles River, where the waters reflect the fading light, could be invigorating. As dusk approaches, don't forget to look up; the clarity of the night sky might reveal a tapestry of stars, a fitting end to a lovely winter day.",
    "color_code": "#1E90FF",
    "timestamp": "2026-01-02 15:08:01"
}