{
    "forecast_data": {
        "location": {
            "name": "Brookline",
            "state": "MA",
            "latitude": 42.287,
            "longitude": -71.133
        },
        "current_conditions": {
            "timestamp": "2024-12-28T02:53:00+00:00",
            "temperature_f": 24.98,
            "temperature_c": -3.9,
            "humidity": 84.677701356961,
            "wind_speed_mph": 0.0,
            "wind_direction": 0,
            "description": "Clear"
        },
        "forecast": [
            {
                "number": 1,
                "name": "Tonight",
                "startTime": "2024-12-27T23:00:00-05:00",
                "endTime": "2024-12-28T06:00:00-05:00",
                "isDaytime": false,
                "temperature": 29,
                "temperatureUnit": "F",
                "temperatureTrend": "",
                "probabilityOfPrecipitation": {
                    "unitCode": "wmoUnit:percent",
                    "value": null
                },
                "windSpeed": "7 mph",
                "windDirection": "SW",
                "icon": "https://api.weather.gov/icons/land/night/bkn?size=medium",
                "shortForecast": "Mostly Cloudy",
                "detailedForecast": "Mostly cloudy, with a low around 29. Southwest wind around 7 mph."
            },
            {
                "number": 2,
                "name": "Saturday",
                "startTime": "2024-12-28T06:00:00-05:00",
                "endTime": "2024-12-28T18:00:00-05:00",
                "isDaytime": true,
                "temperature": 42,
                "temperatureUnit": "F",
                "temperatureTrend": "",
                "probabilityOfPrecipitation": {
                    "unitCode": "wmoUnit:percent",
                    "value": 60
                },
                "windSpeed": "6 mph",
                "windDirection": "S",
                "icon": "https://api.weather.gov/icons/land/day/rain_fzra,60/rain,60?size=medium",
                "shortForecast": "Slight Chance Freezing Rain then Light Rain Likely",
                "detailedForecast": "A slight chance of freezing rain between 7am and 8am, then a chance of rain between 8am and 9am, then rain likely and patchy fog. Cloudy, with a high near 42. South wind around 6 mph. Chance of precipitation is 60%. New rainfall amounts less than a tenth of an inch possible."
            }
        ]
    },
    "weather_report": "As night drapes its serene cloak over Boston, the city nestles into a mostly cloudy embrace, with temperatures hovering around the chill of 29 degrees. A gentle southwest wind whispers through the streets, hinting at the subtle shifts in weather to come. Tomorrow, dawn will bring a hint of tension with a slight chance of freezing rain, flirting briefly with the early morning hours. This is soon followed by a transformation\u2014rain is expected to lace the city in a melancholic shroud, punctuated by patches of fog that could soften the outlines of familiar buildings, rendering them almost dreamlike against the gray backdrop. With a high near 42 degrees, this transition invites not just a change in weather, but perhaps a reflective shift in one\u2019s plans.\n\nAs you prepare for the day ahead, it would serve you well to bundle up in layers that evoke both comfort and practicality: a warm coat, perhaps a snug hat, and sturdy footwear for the inevitable dampness underfoot. Consider setting out for a leisurely stroll through the quieter parts of the city, with the slight aroma of rain mingling in the air, leading you to a cozy caf\u00e9 where you can revel in the simple pleasure of a warm drink while watching the world drift by in its muted colors. Or perhaps a visit to an art gallery, where escaping the weather for a while will nourish your spirit amid the dreary tapestry of the outdoors. In these moments, the weather becomes not just a backdrop but an integral part of the day, inviting stillness in a bustling world.",
    "color_code": "#6C757D",
    "timestamp": "2024-12-27 23:07:27"
}