{
    "forecast_data": {
        "location": {
            "name": "Brookline",
            "state": "MA",
            "latitude": 42.287,
            "longitude": -71.133
        },
        "current_conditions": {
            "timestamp": "2026-01-10T15:50:00+00:00",
            "temperature_f": 42.8,
            "temperature_c": 6,
            "humidity": 65.401134444271,
            "wind_speed_mph": 16.589592000000003,
            "wind_direction": 320,
            "description": "Clear"
        },
        "forecast": [
            {
                "number": 1,
                "name": "Today",
                "startTime": "2026-01-10T11:00:00-05:00",
                "endTime": "2026-01-10T18:00:00-05:00",
                "isDaytime": true,
                "temperature": 45,
                "temperatureUnit": "F",
                "temperatureTrend": null,
                "probabilityOfPrecipitation": {
                    "unitCode": "wmoUnit:percent",
                    "value": 26
                },
                "windSpeed": "5 mph",
                "windDirection": "NE",
                "icon": "https://api.weather.gov/icons/land/day/ovc/rain,30?size=medium",
                "shortForecast": "Cloudy then Chance Light Rain",
                "detailedForecast": "A chance of rain after 5pm. Cloudy. High near 45, with temperatures falling to around 39 in the afternoon. Northeast wind around 5 mph. Chance of precipitation is 30%."
            },
            {
                "number": 2,
                "name": "Tonight",
                "startTime": "2026-01-10T18:00:00-05:00",
                "endTime": "2026-01-11T06:00:00-05:00",
                "isDaytime": false,
                "temperature": 37,
                "temperatureUnit": "F",
                "temperatureTrend": null,
                "probabilityOfPrecipitation": {
                    "unitCode": "wmoUnit:percent",
                    "value": 100
                },
                "windSpeed": "3 to 7 mph",
                "windDirection": "E",
                "icon": "https://api.weather.gov/icons/land/night/rain,100?size=medium",
                "shortForecast": "Light Rain",
                "detailedForecast": "Rain. Cloudy, with a low around 37. East wind 3 to 7 mph. Chance of precipitation is 100%. New rainfall amounts between a quarter and half of an inch possible."
            }
        ]
    },
    "weather_report": "As the sun creeps toward its zenith, the skies over Boston wear a blanket of muted gray, hinting at the moisture that will soon embrace the city. While the chill of the day speaks of a high near 45, it is the creeping clouds that promise rain later in the afternoon, a drenching mere hours away. The air carries a crispness, a gentle northeast breeze stirring the contents of each pocket and jacket, reminding all that winter is still firm in its grasp. The opportunistic chance of precipitation at 30% suggests that one might enjoy a brisk walk or a leisurely coffee at a corner caf\u00e9, all while considering a waterproof layer for the evening that looms.\n\nCome nightfall, that same air will turn heavy with impending rain, bringing solace to the earth as it quenches the thirst brought on by winter\u2019s dry breath. As you prepare for the darkening skies, don your warmer attire\u2014perhaps a cozy sweater under a lightweight waterproof coat, paired with sturdy boots to navigate the slick sidewalks. The prospect of a soaking rain, dressed in the muted tones of clouds, sets the stage for introspection. A perfect evening for a quiet read or an engaging movie, your choices inspired by the rhythm of the weather\u2014reminding you, in the chill of the twilight, that even the most unassuming days can invite moments of peace and reflection.",
    "color_code": "#B0C4DE",
    "timestamp": "2026-01-10 11:07:57"
}