{
    "forecast_data": {
        "location": {
            "name": "Brookline",
            "state": "MA",
            "latitude": 42.287,
            "longitude": -71.133
        },
        "current_conditions": {
            "timestamp": "2026-01-19T04:10:00+00:00",
            "temperature_f": 32.0,
            "temperature_c": 0,
            "humidity": 92.97695284763,
            "wind_speed_mph": 16.589592000000003,
            "wind_direction": 350,
            "description": "Light Snow and Fog/Mist"
        },
        "forecast": [
            {
                "number": 1,
                "name": "Tonight",
                "startTime": "2026-01-18T23:00:00-05:00",
                "endTime": "2026-01-19T06:00:00-05:00",
                "isDaytime": false,
                "temperature": 28,
                "temperatureUnit": "F",
                "temperatureTrend": null,
                "probabilityOfPrecipitation": {
                    "unitCode": "wmoUnit:percent",
                    "value": 78
                },
                "windSpeed": "6 mph",
                "windDirection": "N",
                "icon": "https://api.weather.gov/icons/land/night/snow,80/snow,70?size=medium",
                "shortForecast": "Snow",
                "detailedForecast": "Snow. Cloudy, with a low around 28. North wind around 6 mph. Chance of precipitation is 80%. New snow accumulation of 1 to 3 inches possible."
            },
            {
                "number": 2,
                "name": "M.L. King Jr. Day",
                "startTime": "2026-01-19T06:00:00-05:00",
                "endTime": "2026-01-19T18:00:00-05:00",
                "isDaytime": true,
                "temperature": 34,
                "temperatureUnit": "F",
                "temperatureTrend": null,
                "probabilityOfPrecipitation": {
                    "unitCode": "wmoUnit:percent",
                    "value": 28
                },
                "windSpeed": "3 to 10 mph",
                "windDirection": "W",
                "icon": "https://api.weather.gov/icons/land/day/snow,30/bkn?size=medium",
                "shortForecast": "Light Snow then Mostly Cloudy",
                "detailedForecast": "Snow before 9am, then patchy fog and a slight chance of snow between 9am and 10am. Mostly cloudy, with a high near 34. West wind 3 to 10 mph. Chance of precipitation is 30%. New snow accumulation of less than one inch possible."
            }
        ]
    },
    "weather_report": "As the night blankets Boston, a soft shroud of snow begins to fall, with the world outside gradually transforming into a serene, white canvas. The temperature hovers around a chilly 28 degrees, accompanied by a gentle north wind that whispers through the leafless branches. The atmospheric conditions carry the promise of 1 to 3 inches of fresh snow, enhancing the quiet charm of the city. While the forecast hints at a slight chance of lingering snow into the morning hours, it is the fog that will quietly weave its way through the landscape, softening edges and muffling sounds, creating an intimate and almost ethereal feeling.\n\nTomorrow, as the day unfolds, expect the delicate dance between snow and fog to persist until mid-morning. A high nearing 34 degrees will offer a timid warmth, but the lingering clouds will keep the light subdued, evoking a sense of calm rather than vibrancy. For those venturing outside, layering is advisable; a cozy scarf and a sturdy pair of boots will shield you from the chill and assistance in navigating the occasional slick surfaces. As snowflakes flurry around, consider cozy indoor pursuits\u2014a visit to a quaint caf\u00e9 for a steaming cup of cocoa or a leisurely stroll through a quiet park, where the delicate crunch of snow underfoot accompanies the gentle fall. In this mellow winter landscape, a tender embrace of nature awaits, inviting moments of reflection and tranquility.",
    "color_code": "#B0C4DE",
    "timestamp": "2026-01-18 23:28:26"
}