{
    "forecast_data": {
        "location": {
            "name": "Brookline",
            "state": "MA",
            "latitude": 42.287,
            "longitude": -71.133
        },
        "current_conditions": {
            "timestamp": "2025-05-30T17:53:00+00:00",
            "temperature_f": 73.94,
            "temperature_c": 23.3,
            "humidity": 63.96353937857,
            "wind_speed_mph": 41.07132,
            "wind_direction": 200,
            "description": "Cloudy"
        },
        "forecast": [
            {
                "number": 1,
                "name": "This Afternoon",
                "startTime": "2025-05-30T16:00:00-04:00",
                "endTime": "2025-05-30T18:00:00-04:00",
                "isDaytime": true,
                "temperature": 76,
                "temperatureUnit": "F",
                "temperatureTrend": "",
                "probabilityOfPrecipitation": {
                    "unitCode": "wmoUnit:percent",
                    "value": 19
                },
                "windSpeed": "10 mph",
                "windDirection": "SW",
                "icon": "https://api.weather.gov/icons/land/day/rain_showers,20?size=medium",
                "shortForecast": "Slight Chance Rain Showers",
                "detailedForecast": "A slight chance of rain showers before 5pm. Partly sunny, with a high near 76. Southwest wind around 10 mph. Chance of precipitation is 20%. New rainfall amounts less than a tenth of an inch possible."
            },
            {
                "number": 2,
                "name": "Tonight",
                "startTime": "2025-05-30T18:00:00-04:00",
                "endTime": "2025-05-31T06:00:00-04:00",
                "isDaytime": false,
                "temperature": 58,
                "temperatureUnit": "F",
                "temperatureTrend": "",
                "probabilityOfPrecipitation": {
                    "unitCode": "wmoUnit:percent",
                    "value": 88
                },
                "windSpeed": "5 to 9 mph",
                "windDirection": "S",
                "icon": "https://api.weather.gov/icons/land/night/bkn/tsra,90?size=medium",
                "shortForecast": "Mostly Cloudy then Slight Chance Showers And Thunderstorms",
                "detailedForecast": "A slight chance of rain showers between 1am and 2am, then a slight chance of showers and thunderstorms between 2am and 3am, then showers and thunderstorms. Mostly cloudy, with a low around 58. South wind 5 to 9 mph. Chance of precipitation is 90%. New rainfall amounts between a quarter and half of an inch possible."
            }
        ]
    },
    "weather_report": "This afternoon in Boston, the skies are adorned with a delicate tapestry of clouds teasing a hint of sunshine, as a gentle southwest breeze carries warmth through the air. The chance of light rain is on the horizon, though the day beckons one to glimpse the beauty before the clouds inevitably gather. As the hours tilt toward evening, the atmosphere shifts, heralding an approach of showers and potential thunderstorms in the night. The temperature, a comforting wrap of warmth in the mid-seventies, invites light clothing, perhaps a breath of linen or soft cotton, but the shifting winds suggest reconsidering that final outfit of the day with an eye toward somber hues for the impending storms.\n\nAs twilight dances near, one may find solace in a neighborhood caf\u00e9, clutching a warm drink as the skies transform, or taking a leisurely stroll under the clouds, enjoying the fragrance of rain-soaked earth before the showers drench the pavement. An evening spent by the window, listening to the distant rumble of thunder may also be the perfect welcome for the rainy night ahead. With the uncertainties of the weather whispering of action, yet holding a breath of calm, embracing the subtle transitions of the day becomes a delightful adventure in itself, urging one to be prepared for the beauty of nature in all its vibrant forms.",
    "color_code": "#B0C4DE",
    "timestamp": "2025-05-30 16:07:46"
}