{
    "forecast_data": {
        "location": {
            "name": "Brookline",
            "state": "MA",
            "latitude": 42.287,
            "longitude": -71.133
        },
        "current_conditions": {
            "timestamp": "2025-06-09T06:53:00+00:00",
            "temperature_f": 60.08,
            "temperature_c": 15.6,
            "humidity": 77.603412846276,
            "wind_speed_mph": 12.0798,
            "wind_direction": 90,
            "description": "Cloudy"
        },
        "forecast": [
            {
                "number": 1,
                "name": "Overnight",
                "startTime": "2025-06-09T04:00:00-04:00",
                "endTime": "2025-06-09T06:00:00-04:00",
                "isDaytime": false,
                "temperature": 55,
                "temperatureUnit": "F",
                "temperatureTrend": "",
                "probabilityOfPrecipitation": {
                    "unitCode": "wmoUnit:percent",
                    "value": 16
                },
                "windSpeed": "7 mph",
                "windDirection": "E",
                "icon": "https://api.weather.gov/icons/land/night/rain_showers,20?size=medium",
                "shortForecast": "Slight Chance Rain Showers",
                "detailedForecast": "A slight chance of rain showers. Mostly cloudy, with a low around 55. East wind around 7 mph. Chance of precipitation is 20%."
            },
            {
                "number": 2,
                "name": "Monday",
                "startTime": "2025-06-09T06:00:00-04:00",
                "endTime": "2025-06-09T18:00:00-04:00",
                "isDaytime": true,
                "temperature": 65,
                "temperatureUnit": "F",
                "temperatureTrend": "",
                "probabilityOfPrecipitation": {
                    "unitCode": "wmoUnit:percent",
                    "value": 23
                },
                "windSpeed": "10 mph",
                "windDirection": "E",
                "icon": "https://api.weather.gov/icons/land/day/rain_showers,20?size=medium",
                "shortForecast": "Slight Chance Rain Showers",
                "detailedForecast": "A slight chance of rain showers. Mostly cloudy, with a high near 65. East wind around 10 mph. Chance of precipitation is 20%."
            }
        ]
    },
    "weather_report": "As the first light of day begins to creep over Boston, a veil of clouds lingers in the sky, casting a muted glow across the landscape. The early hours are marked by a gentle chill, with temperatures resting at around 55 degrees, and an eastward breeze that adds a soft touch to the otherwise still morning. Although the forecast hints at a slight chance of rain, the city remains calm, suggesting that any drops will be light and fleeting. It\u2019s a moment where nature holds its breath, waiting to unfold a day that promises both clouds and perhaps a glimpse of sunshine.\n\nAs the day progresses, Boston's charm will continue to shine through the overcast skies. Residents can expect a high nearing 65 degrees, making it an ideal time for light layers\u2014perhaps a cozy sweater paired with a light jacket if venturing out. The ambiance of the day invites leisurely strolls, a visit to a local caf\u00e9 to savor a comforting cup of coffee, or simply basking in the beauty of this transitional season. While errands might require umbrellas at the ready, they also beckon opportunities to enjoy the rhythm of life unhurriedly, embracing all this slightly somber yet enchanting day has to offer.",
    "color_code": "#B0B0B0",
    "timestamp": "2025-06-09 04:10:58"
}