{
    "forecast_data": {
        "location": {
            "name": "Brookline",
            "state": "MA",
            "latitude": 42.287,
            "longitude": -71.133
        },
        "current_conditions": {
            "timestamp": "2025-03-07T06:53:00+00:00",
            "temperature_f": 35.06,
            "temperature_c": 1.7,
            "humidity": 51.659168100404,
            "wind_speed_mph": 57.98304000000001,
            "wind_direction": 290,
            "description": "Mostly Cloudy"
        },
        "forecast": [
            {
                "number": 1,
                "name": "Overnight",
                "startTime": "2025-03-07T03:00:00-05:00",
                "endTime": "2025-03-07T06:00:00-05:00",
                "isDaytime": false,
                "temperature": 29,
                "temperatureUnit": "F",
                "temperatureTrend": "",
                "probabilityOfPrecipitation": {
                    "unitCode": "wmoUnit:percent",
                    "value": null
                },
                "windSpeed": "23 mph",
                "windDirection": "W",
                "icon": "https://api.weather.gov/icons/land/night/wind_sct?size=medium",
                "shortForecast": "Partly Cloudy",
                "detailedForecast": "Partly cloudy, with a low around 29. West wind around 23 mph, with gusts as high as 38 mph."
            },
            {
                "number": 2,
                "name": "Friday",
                "startTime": "2025-03-07T06:00:00-05:00",
                "endTime": "2025-03-07T18:00:00-05:00",
                "isDaytime": true,
                "temperature": 41,
                "temperatureUnit": "F",
                "temperatureTrend": "",
                "probabilityOfPrecipitation": {
                    "unitCode": "wmoUnit:percent",
                    "value": null
                },
                "windSpeed": "22 to 26 mph",
                "windDirection": "W",
                "icon": "https://api.weather.gov/icons/land/day/wind_few?size=medium",
                "shortForecast": "Sunny",
                "detailedForecast": "Sunny, with a high near 41. West wind 22 to 26 mph, with gusts as high as 44 mph."
            }
        ]
    },
    "weather_report": "As the night deepens over Boston, the air carries a crisp bite\u2014a harbinger of the chilly dawn ahead. The streets shimmer quietly beneath a faint veil as the city nestles into its slumber, but do not let the tranquillity fool you. The winds, bold and unyielding, will soon awaken, gusting fiercely from the west. This is a night where warmth becomes a luxury, and if you must step out to greet the morning, a snug coat, gloves, and a sturdy hat are your allies against the brisk embrace of the cooling atmosphere.\n\nCome the light of day, Boston will unfurl beneath a bright azure sky, offering a straightforward cheerfulness. The sun will reign high, a welcome sight, yet the relentless winds will not forget their duty, bustling through the avenues and across the parks, making each step a brisk one. It beckons those who love the invigorating touch of nature to venture outside, perhaps for a brisk walk along the Charles River, where even the simplest act of strolling transforms into a spirited dance with the elements. Tailored layers will serve you well, as the warmth of the sun struggles against the cool whispers of the wind. Engage with your surroundings, grab a coffee from a local caf\u00e9, and allow this robust winter day to fill your senses with the vibrancy of the season, enriching the heart of a strong city.",
    "color_code": "#3C3F41",
    "timestamp": "2025-03-07 03:08:53"
}