{
    "forecast_data": {
        "location": {
            "name": "Brookline",
            "state": "MA",
            "latitude": 42.287,
            "longitude": -71.133
        },
        "current_conditions": {
            "timestamp": "2025-01-20T05:53:00+00:00",
            "temperature_f": 30.02,
            "temperature_c": -1.1,
            "humidity": 81.277356533637,
            "wind_speed_mph": 28.991520000000005,
            "wind_direction": 320,
            "description": "Light Snow"
        },
        "forecast": [
            {
                "number": 1,
                "name": "Overnight",
                "startTime": "2025-01-20T03:00:00-05:00",
                "endTime": "2025-01-20T06:00:00-05:00",
                "isDaytime": false,
                "temperature": 16,
                "temperatureUnit": "F",
                "temperatureTrend": "",
                "probabilityOfPrecipitation": {
                    "unitCode": "wmoUnit:percent",
                    "value": 70
                },
                "windSpeed": "14 mph",
                "windDirection": "NW",
                "icon": "https://api.weather.gov/icons/land/night/snow,70?size=medium",
                "shortForecast": "Light Snow Likely",
                "detailedForecast": "Snow likely. Cloudy, with a low around 16. Northwest wind around 14 mph, with gusts as high as 26 mph. Chance of precipitation is 70%. New snow accumulation of less than half an inch possible."
            },
            {
                "number": 2,
                "name": "M.L. King Jr. Day",
                "startTime": "2025-01-20T06:00:00-05:00",
                "endTime": "2025-01-20T18:00:00-05:00",
                "isDaytime": true,
                "temperature": 25,
                "temperatureUnit": "F",
                "temperatureTrend": "",
                "probabilityOfPrecipitation": {
                    "unitCode": "wmoUnit:percent",
                    "value": null
                },
                "windSpeed": "9 to 14 mph",
                "windDirection": "W",
                "icon": "https://api.weather.gov/icons/land/day/sct?size=medium",
                "shortForecast": "Mostly Sunny",
                "detailedForecast": "Mostly sunny, with a high near 25. West wind 9 to 14 mph, with gusts as high as 25 mph."
            }
        ]
    },
    "weather_report": "As the gentle hours of the night unfurl over Boston, a quiet snow signals its arrival, blanketing the city with a delicate touch. The air hangs crisp and sharp, carrying whispers of a northwest wind that dances at a brisk pace. The low temperature drapes a mantle of chill, suggesting that layers will be your steadfast companions. As you venture into the early morning, consider wrapping yourself in warm attire\u2014perhaps a sturdy coat, a cozy scarf, and gloves\u2014perfect for holding a hot cup of coffee while gazing at the serene landscape transformed by this light snowfall.\n\nAs dawn breaks, the promise of a mostly sunny day emerges. The sunlight will greet Boston with a sparkle, illuminating the crispness of the snow and inviting you outdoors. The temperature will rise, but it will retain a coolness that evokes the essence of winter, making it an ideal setting for a leisurely walk through the city\u2019s quaint streets or a visit to a local caf\u00e9 for a warm pastry. This day has a pleasant charm, perfect for savoring simple moments, whether you choose to explore the snow-dusted people\u2019s park or encounter the warm hospitality of city shops, each a little refuge from the lingering chill.",
    "color_code": "#B0C4DE",
    "timestamp": "2025-01-20 03:08:58"
}