{
    "forecast_data": {
        "location": {
            "name": "Brookline",
            "state": "MA",
            "latitude": 42.287,
            "longitude": -71.133
        },
        "current_conditions": {
            "timestamp": "2025-10-01T03:50:00+00:00",
            "temperature_f": 48.2,
            "temperature_c": 9,
            "humidity": 100,
            "wind_speed_mph": 0.0,
            "wind_direction": 0,
            "description": "Clear"
        },
        "forecast": [
            {
                "number": 1,
                "name": "Overnight",
                "startTime": "2025-10-01T00:00:00-04:00",
                "endTime": "2025-10-01T06:00:00-04:00",
                "isDaytime": false,
                "temperature": 51,
                "temperatureUnit": "F",
                "temperatureTrend": "",
                "probabilityOfPrecipitation": {
                    "unitCode": "wmoUnit:percent",
                    "value": 0
                },
                "windSpeed": "8 to 13 mph",
                "windDirection": "NE",
                "icon": "https://api.weather.gov/icons/land/night/few?size=medium",
                "shortForecast": "Mostly Clear",
                "detailedForecast": "Mostly clear, with a low around 51. Northeast wind 8 to 13 mph."
            },
            {
                "number": 2,
                "name": "Wednesday",
                "startTime": "2025-10-01T06:00:00-04:00",
                "endTime": "2025-10-01T18:00:00-04:00",
                "isDaytime": true,
                "temperature": 62,
                "temperatureUnit": "F",
                "temperatureTrend": "",
                "probabilityOfPrecipitation": {
                    "unitCode": "wmoUnit:percent",
                    "value": 0
                },
                "windSpeed": "15 mph",
                "windDirection": "NE",
                "icon": "https://api.weather.gov/icons/land/day/few?size=medium",
                "shortForecast": "Sunny",
                "detailedForecast": "Sunny, with a high near 62. Northeast wind around 15 mph, with gusts as high as 26 mph."
            }
        ]
    },
    "weather_report": "In the stillness of the night, Boston lies beneath a canopy of stars, shimmering lights flickering against the darkness like distant dreams. The air is crisp, hinting at the day's promise, and though the chill of early October lingers, it breathes freshness into the lungs. As dawn approaches, the curtain of night will lift to reveal a sun-drenched Wednesday, where warmth blooms like the soft unfurling of flowers, tempered by a playful northeast breeze that carries a sense of adventure in its whispers.\n\nBy midday, the sun will illuminate the cityscape, casting long shadows over the cobblestones and revealing Boston\u2019s historic charm in vibrant hues. It will be the sort of day that invites wanderers to stroll amongst the riverbanks or visit quaint caf\u00e9s\u2014each with a steaming cup cradled in hand while the wind tousles hair and spirits alike. Dress comfortably and warmly in layers, perhaps a light sweater paired with a stylish jacket, ready to embrace the sunshine and the brisk breeze. Whether it\u2019s soaking in the rich culture at the museums or meandering through serene parks, today beckons residents to step outside, breathe deeply, and relish the brightness, even as the shortness of the day whispers of the longer nights to come.",
    "color_code": "#A4C8E1",
    "timestamp": "2025-10-01 00:08:55"
}