{
    "forecast_data": {
        "location": {
            "name": "Brookline",
            "state": "MA",
            "latitude": 42.287,
            "longitude": -71.133
        },
        "current_conditions": {
            "timestamp": "2025-06-22T01:53:00+00:00",
            "temperature_f": 75.02,
            "temperature_c": 23.9,
            "humidity": 68.710075389143,
            "wind_speed_mph": 12.0798,
            "wind_direction": 180,
            "description": ""
        },
        "forecast": [
            {
                "number": 1,
                "name": "Overnight",
                "startTime": "2025-06-22T00:00:00-04:00",
                "endTime": "2025-06-22T06:00:00-04:00",
                "isDaytime": false,
                "temperature": 70,
                "temperatureUnit": "F",
                "temperatureTrend": "",
                "probabilityOfPrecipitation": {
                    "unitCode": "wmoUnit:percent",
                    "value": 6
                },
                "windSpeed": "7 mph",
                "windDirection": "SW",
                "icon": "https://api.weather.gov/icons/land/night/bkn?size=medium",
                "shortForecast": "Mostly Cloudy",
                "detailedForecast": "Mostly cloudy, with a low around 70. Southwest wind around 7 mph."
            },
            {
                "number": 2,
                "name": "Sunday",
                "startTime": "2025-06-22T06:00:00-04:00",
                "endTime": "2025-06-22T18:00:00-04:00",
                "isDaytime": true,
                "temperature": 94,
                "temperatureUnit": "F",
                "temperatureTrend": "",
                "probabilityOfPrecipitation": {
                    "unitCode": "wmoUnit:percent",
                    "value": 31
                },
                "windSpeed": "12 to 17 mph",
                "windDirection": "W",
                "icon": "https://api.weather.gov/icons/land/day/tsra_sct,30/hot?size=medium",
                "shortForecast": "Slight Chance Showers And Thunderstorms then Partly Sunny",
                "detailedForecast": "A slight chance of showers and thunderstorms between 7am and 8am, then a chance of showers and thunderstorms between 8am and noon. Partly sunny, with a high near 94. Heat index values as high as 99. West wind 12 to 17 mph, with gusts as high as 28 mph. Chance of precipitation is 30%. New rainfall amounts less than a tenth of an inch possible."
            }
        ]
    },
    "weather_report": "As midnight cloaks Boston in its still embrace, the air is warm and inviting, holding a low temperature around 70. The night sky, draped in a veil of clouds, whispers promises of a vibrant dawn. A gentle southwesterly breeze rustles through the trees, hinting at the balmy revelry that the day will bring. As morning unfurls, expect a flirtation with thunderstorms, though only a slight chance at first light. The sun will soon shy away, giving way to a tapestry of partly sunny skies that will beckon you outdoors.\n\nBy midday, temperatures will climb toward a sweltering 94, with the heat index pushing the day into the realms of discomfort. It will feel heavy, as though the air itself is a warm embrace. In such weather, dressing lightly becomes a necessity; cottons and loose fabrics will shield you against the rising warmth, while a hint of a breeze may offer fleeting respite. Consider venturing into the shade of local parks or indulging in a casual stroll along the Esplanade, where the sounds of whispers and laughter mingle with the rustle of leaves. As the day progresses, don\u2019t forget to stay hydrated, perhaps savoring a cool iced beverage from a nearby caf\u00e9. Whether it be engaging in quiet moments of reflection or enjoying the company of friends, this summer day promises to unfold with its own sense of casual charm.",
    "color_code": "#F0E68C",
    "timestamp": "2025-06-22 00:14:51"
}