{
    "forecast_data": {
        "location": {
            "name": "Brookline",
            "state": "MA",
            "latitude": 42.287,
            "longitude": -71.133
        },
        "current_conditions": {
            "timestamp": "2026-01-17T18:35:00+00:00",
            "temperature_f": 37.4,
            "temperature_c": 3,
            "humidity": 64.714825534266,
            "wind_speed_mph": 16.589592000000003,
            "wind_direction": 310,
            "description": "Cloudy"
        },
        "forecast": [
            {
                "number": 1,
                "name": "This Afternoon",
                "startTime": "2026-01-17T15:00:00-05:00",
                "endTime": "2026-01-17T18:00:00-05:00",
                "isDaytime": true,
                "temperature": 44,
                "temperatureUnit": "F",
                "temperatureTrend": null,
                "probabilityOfPrecipitation": {
                    "unitCode": "wmoUnit:percent",
                    "value": 37
                },
                "windSpeed": "7 mph",
                "windDirection": "SW",
                "icon": "https://api.weather.gov/icons/land/day/rain,40?size=medium",
                "shortForecast": "Chance Light Rain",
                "detailedForecast": "A chance of rain. Mostly cloudy, with a high near 44. Southwest wind around 7 mph. Chance of precipitation is 40%. New rainfall amounts less than a tenth of an inch possible."
            },
            {
                "number": 2,
                "name": "Tonight",
                "startTime": "2026-01-17T18:00:00-05:00",
                "endTime": "2026-01-18T06:00:00-05:00",
                "isDaytime": false,
                "temperature": 30,
                "temperatureUnit": "F",
                "temperatureTrend": null,
                "probabilityOfPrecipitation": {
                    "unitCode": "wmoUnit:percent",
                    "value": 17
                },
                "windSpeed": "3 to 7 mph",
                "windDirection": "SW",
                "icon": "https://api.weather.gov/icons/land/night/rain,20/bkn?size=medium",
                "shortForecast": "Slight Chance Light Rain then Mostly Cloudy",
                "detailedForecast": "A slight chance of rain before 7pm. Mostly cloudy, with a low around 30. Southwest wind 3 to 7 mph. Chance of precipitation is 20%."
            }
        ]
    },
    "weather_report": "In Boston this afternoon, the air carries a notable chill, draped in a dense, grayish shroud that hints at the possibility of rain. Though the clouds loom heavily, the warmth of the sun is merely a distant memory, with a high nearing 44 degrees gently teasing any hopes of brightness. A soft, southwestern wind carries whispers of moisture, creating a scene that feels introverted and contemplative. As the clock ticks toward evening, the slight chance of rain before 7 p.m. lingers like a half-formed thought, inviting the city\u2019s inhabitants to seek comfort indoors as day turns to dusk.\n\nGiven the chill, especially as temperatures dip to around 30 tonight, a layered approach to dressing is prudent. A cozy sweater beneath a water-resistant coat would serve well against the brisk air, accompanied by a warm scarf and sturdy shoes to navigate the damp sidewalks. In such a day, one might choose to embrace the indoor comforts, perhaps visiting a quiet caf\u00e9 with a well-worn book or opting for a leisurely stroll through the hushed city streets, taking in the moody landscape while sipping a warm drink. Tonight, as the light fades, a cozy gathering with friends or a cherished movie might just bring warmth to match the chill of the evening.",
    "color_code": "#B0B0B0",
    "timestamp": "2026-01-17 15:07:28"
}